dff.v
`timescale 1ns/1ps

module dff (
    input clk,
    input rst,
    input d,
    output reg q
);

always @(posedge clk or posedge rst) begin
    if (rst)
        q <= 1'b0;
    else
        q <= d;
end

endmodule

tb.v
`timescale 1ns/1ps

module tb;

reg clk;
reg rst;
reg d;
wire q;

dff dut (
    .clk(clk),
    .rst(rst),
    .d(d),
    .q(q)
);

always #5 clk = ~clk;

initial begin
    $dumpfile("dff.vcd");
    $dumpvars(0,tb);

    clk = 0;
    rst = 1;
    d   = 0;

    #10 rst = 0;
    #10 d = 1;
    #10 d = 0;
    #10 d = 1;
    #10 rst = 1;
    #10 rst = 0;
    #10 d = 0;
    #20 $finish;
end

always @(posedge clk) begin
    $display("time=%0t d=%b q=%b", $time, d, q);
end

endmodule

dff.vcd
$version Generated by VerilatedVcd $end
$timescale 1ps $end
 $scope module tb $end
  $var wire 1 " clk $end
  $var wire 1 # rst $end
  $var wire 1 $ d $end
  $var wire 1 % q $end
  $scope module dut $end
   $var wire 1 " clk $end
   $var wire 1 # rst $end
   $var wire 1 $ d $end
   $var wire 1 % q $end
  $upscope $end
 $upscope $end
$enddefinitions $end


#0
0"
1#
0$
0%
#5000
1"
#10000
0"
0#
#15000
1"
#20000
0"
1$
#25000
1"
1%
#30000
0"
0$
#35000
1"
0%
#40000
0"
1$
#45000
1"
1%
#50000
0"
1#
0%
#55000
1"
#60000
0"
0#
#65000
1"
1%
#70000
0"
0$
#75000
1"
0%
